openhands_dynamic_agent_factory/__init__.py
openhands_dynamic_agent_factory/core/__init__.py
openhands_dynamic_agent_factory/core/dynamic_agent_factory.py
openhands_dynamic_agent_factory/core/dynamic_agent_factory_llm.py
openhands_dynamic_agent_factory/core/factory.py
openhands_dynamic_agent_factory/core/triggers.py
openhands_dynamic_agent_factory-0.1.0.dist-info/LICENSE
openhands_dynamic_agent_factory-0.1.0.dist-info/METADATA
openhands_dynamic_agent_factory-0.1.0.dist-info/WHEEL
openhands_dynamic_agent_factory-0.1.0.dist-info/top_level.txt
openhands_dynamic_agent_factory-0.1.0.dist-info/RECORD
