Metadata-Version: 2.1
Name: openhands_dynamic_agent_factory
Version: 0.1.0
Summary: Dynamic agent factory for OpenHands that generates micro-agents based on technology keywords
Author-email: Makafeli <info@yasin.nu>
Project-URL: Homepage, https://github.com/makafeli/openhands-dynamic-agent-factor
Project-URL: Bug Tracker, https://github.com/makafeli/openhands-dynamic-agent-factor/issues
Keywords: openhands,llm,agent,factory,code-analysis
Classifier: Development Status :: 3 - Alpha
Classifier: Intended Audience :: Developers
Classifier: License :: OSI Approved :: MIT License
Classifier: Programming Language :: Python :: 3
Classifier: Programming Language :: Python :: 3.7
Classifier: Programming Language :: Python :: 3.8
Classifier: Programming Language :: Python :: 3.9
Classifier: Programming Language :: Python :: 3.10
Classifier: Programming Language :: Python :: 3.11
Classifier: Programming Language :: Python :: 3.12
Requires-Python: >=3.7
License-File: LICENSE
Requires-Dist: openhands>=0.17.0
Requires-Dist: dataclasses; python_version < "3.7"
Provides-Extra: python
Requires-Dist: ast; extra == "python"
Requires-Dist: pylint>=3.0.0; extra == "python"
Provides-Extra: react
Requires-Dist: esprima>=4.0.0; extra == "react"
Requires-Dist: eslint>=8.0.0; extra == "react"
Provides-Extra: node
Requires-Dist: acorn>=8.0.0; extra == "node"
Requires-Dist: eslint>=8.0.0; extra == "node"
Provides-Extra: sql
Requires-Dist: sqlparse>=0.4.0; extra == "sql"
Requires-Dist: sqlalchemy>=2.0.0; extra == "sql"
Provides-Extra: dev
Requires-Dist: pytest>=7.0.0; extra == "dev"
Requires-Dist: pytest-cov>=4.0.0; extra == "dev"
Requires-Dist: black>=23.0.0; extra == "dev"
Requires-Dist: isort>=5.0.0; extra == "dev"
Requires-Dist: mypy>=1.0.0; extra == "dev"
Requires-Dist: flake8>=6.0.0; extra == "dev"
Provides-Extra: all
Requires-Dist: ast; extra == "all"
Requires-Dist: pylint>=3.0.0; extra == "all"
Requires-Dist: esprima>=4.0.0; extra == "all"
Requires-Dist: eslint>=8.0.0; extra == "all"
Requires-Dist: acorn>=8.0.0; extra == "all"
Requires-Dist: sqlparse>=0.4.0; extra == "all"
Requires-Dist: sqlalchemy>=2.0.0; extra == "all"
